MANIFEST.in
README.rst
setup.py
clix/__init__.py
clix/clips_data
clix/clix.py
clix/config
clix/gui.py
clix/icon.png
clix/pyxhook.py
clix/utils.py
clix.egg-info/PKG-INFO
clix.egg-info/SOURCES.txt
clix.egg-info/dependency_links.txt
clix.egg-info/entry_points.txt
clix.egg-info/not-zip-safe
clix.egg-info/requires.txt
clix.egg-info/top_level.txt